drf_polymorphic/__init__.py
drf_polymorphic/apps.py
drf_polymorphic/extensions.py
drf_polymorphic/py.typed
drf_polymorphic/serializers.py
drf_polymorphic-2.1.1.dist-info/licenses/LICENSE
drf_polymorphic-2.1.1.dist-info/METADATA
drf_polymorphic-2.1.1.dist-info/WHEEL
drf_polymorphic-2.1.1.dist-info/top_level.txt
drf_polymorphic-2.1.1.dist-info/RECORD
