Metadata-Version: 2.4
Name: drf-polymorphic
Version: 2.1.1
Summary: Polymorphic serializers without models
Home-page: https://github.com/maykinmedia/drf-polymorphic
Author: Maykin Media
Author-email: support@maykinmedia.nl
License: MIT
Project-URL: Documentation, http://drf-polymorphic.readthedocs.io/en/latest/
Project-URL: Changelog, https://github.com/maykinmedia/drf-polymorphic/blob/main/docs/changelog.rst
Project-URL: Bug Tracker, https://github.com/maykinmedia/drf-polymorphic/issues
Project-URL: Source Code, https://github.com/maykinmedia/drf-polymorphic
Keywords: django,rest,polymorphic
Classifier: Development Status :: 5 - Production/Stable
Classifier: Framework :: Django
Classifier: Framework :: Django :: 4.2
Classifier: Framework :: Django :: 5.2
Classifier: Intended Audience :: Developers
Classifier: Operating System :: Unix
Classifier: Operating System :: MacOS
Classifier: Operating System :: Microsoft :: Windows
Classifier: Programming Language :: Python :: 3.10
Classifier: Programming Language :: Python :: 3.11
Classifier: Programming Language :: Python :: 3.12
Classifier: Topic :: Software Development :: Libraries :: Python Modules
License-File: LICENSE
Requires-Dist: django>=4.2
Requires-Dist: djangorestframework>=3.13
Provides-Extra: spectacular
Requires-Dist: drf-spectacular; extra == "spectacular"
Provides-Extra: tests
Requires-Dist: drf-spectacular; extra == "tests"
Requires-Dist: djangorestframework-camel-case; extra == "tests"
Requires-Dist: pytest; extra == "tests"
Requires-Dist: pytest-django; extra == "tests"
Requires-Dist: hypothesis; extra == "tests"
Requires-Dist: tox; extra == "tests"
Requires-Dist: isort; extra == "tests"
Requires-Dist: black; extra == "tests"
Requires-Dist: flake8; extra == "tests"
Requires-Dist: mypy; extra == "tests"
Requires-Dist: django-stubs[compatible-mypy]; extra == "tests"
Requires-Dist: djangorestframework-stubs[compatible-mypy]; extra == "tests"
Provides-Extra: coverage
Requires-Dist: pytest-cov; extra == "coverage"
Provides-Extra: docs
Requires-Dist: sphinx; extra == "docs"
Requires-Dist: sphinx-rtd-theme; extra == "docs"
Provides-Extra: release
Requires-Dist: bump2version; extra == "release"
Requires-Dist: twine; extra == "release"
Dynamic: license-file
